.travis.yml
LICENSE
README.md
requirements.txt
setup.cfg
setup.py
infuse/__init__.py
infuse/config.py
infuse.egg-info/PKG-INFO
infuse.egg-info/SOURCES.txt
infuse.egg-info/dependency_links.txt
infuse.egg-info/entry_points.txt
infuse.egg-info/not-zip-safe
infuse.egg-info/pbr.json
infuse.egg-info/requires.txt
infuse.egg-info/top_level.txt
infuse/client/__init__.py
infuse/database/__init__.py
infuse/database/cli.py
infuse/database/models.py
infuse/server/__init__.py
infuse/server/cli.py
infuse/server/routes/__init__.py
infuse/server/routes/home.py
samples/infuse.conf